Workbook

Sheet Dashboard
A1: Smart Bin — Project Dashboard
A2: Live overview — recalculates from the tabs below, nothing to type here
A4: TOTAL BUDGET (EUR) | C4: TOTAL SPENT (EUR) | E4: REMAINING BUDGET (EUR) | G4: % BUDGET USED
A5: ='Budget by Category'!B14 -> 0 | C5: ='Budget by Category'!C14 -> 41.68 | E5: ='Budget by Category'!D14 -> -41.68 | G5: ='Budget by Category'!E14
A7: EXPENDITURE ENTRIES | C7: MEETINGS LOGGED | E7: MEETINGS COMPLETED | G7: OPEN ACTION ITEMS
A8: =COUNTIF('Expenditure Registry'!A4:A43,"E*") -> 40 | C8: =COUNTIF('Meeting Log'!A4:A33,"M*") -> 1 | E8: =COUNTIFS('Meeting Log'!A4:A33,"M*",'Meeting Log'!I4:I33,"Completed") -> 1 | G8: =COUNTIFS('Action Items'!A4:A33,"A*",'Action Items'!H4:H33,"<>Done") -> 1
A11: Budget vs. Actual by Category

Sheet Instructions
A1: Smart Bin — Project Registry
A2: How to use this workbook
B5: Purpose | C5: A single-file operations registry for the Smart Bin project: expenditure, budget vs. actual, meeting log, and action items — a lightweight Notion-style database, kept as plain, versionable spreadsheet tabs.
B6: How to fill it in | C6: Each log tab (Expenditure Registry, Meeting Log, Action Items) has one example row marked "EXAMPLE — replace or delete" in row 3, followed by blank pre-formatted rows with dropdown validation. Type over the example row first, then continue down the blank rows. IDs follow the prefix shown (E for expenditure, M for meetings, A for action items) — just increment the number.
B7: Editable cells | C7: Cells shaded yellow are the ones meant to be typed into (e.g. FX Rate, Budgeted amounts). White cells with dropdowns are also meant to be filled in — the dropdown just constrains the options. Cells in black text with formulas (e.g. Amount (EUR), Actual Spent, all Dashboard tiles) are calculated automatically — do not overwrite them.
B8: Currency | C8: Log each expense in its original currency (Amount + Currency), then set the FX Rate to EUR used on that date (e.g. from ECB reference rates). Amount (EUR) is computed automatically and is what the Budget and Dashboard tabs total. For EUR expenses, just set the rate to 1.
B9: Dashboard | C9: The Dashboard tab is fully computed from the other four tabs — nothing to type there. It re-totals automatically whenever you add rows to the logs below it.
B10: Adding rows | C10: If you run out of blank template rows, insert new rows *above* the TOTAL row in that table and copy the formatting/formulas from the row above — Excel/LibreOffice will extend the SUMIFS/COUNTIF ranges automatically since they reference full columns.
B11: Tabs | C11: 1. Dashboard — live KPI overview 2. Expenditure Registry — every purchase, tool subscription, or reimbursement 3. Budget by Category — budget vs. actual, by spend category 4. Meeting Log — founders' meetings, decisions, attendees 5. Action Items — tasks raised in meetings, owners, due dates, status
B13: Color legend
C14: Type in this cell — direct input (amounts, budgets, dates, free text)
C15: Type in this cell or pick from dropdown list
C16: Calculated automatically — formula, do not overwrite
B18: Maintainers | C18: Smart Bin founders — Bioinformatics / Mathematics / Physics backgrounds. See CLAUDE.md and docs/ in the repository for the product roadmap and engineering decisions this registry supports.

Sheet Expenditure Registry
A1: Expenditure Registry
A2: Every purchase, subscription, or reimbursement — logged as it happens
A3: ID | B3: Date | C3: Category | D3: Description | E3: Vendor / Supplier | F3: Amount (EUR) | G3: Payment Method | H3: Paid By | I3: Status | J3: Invoice / Receipt Ref | K3: Notes
A4: E001 | B4: 46226 | C4: Hardware Components | D4: Seeed Studio XIAO ESP32S3 Sense (5x dev units) — EXAMPLE, replace or delete | E4: Seeed Studio | F4: 19.9 | G4: Other | H4: Roger | I4: Paid | J4: INV-2026-0043 | K4: Initial batch for perception module prototyping
A5: E002 | B5: 46224 | C5: AI/Compute & Cloud | D5: Claude Pro subcription | E5: claude | F5: 21.78 | G5: Other | H5: Roger | I5: Paid
A6: E003
A7: E004
A8: E005
A9: E006
A10: E007
A11: E008
A12: E009
A13: E010
A14: E011
A15: E012
A16: E013
A17: E014
... A43: E040
F44: =SUM(F4:F43) -> 41.68

Sheet Budget by Category
A1: Budget by Category
A2: Budget vs. actual, pulled live from the Expenditure Registry
A3: Category | B3: Budgeted (EUR) | C3: Actual Spent (EUR) | D3: Variance (EUR) | E3: % of Budget Used | F3: Status
A4: Hardware Components | B4: 0 | C4: =SUMIFS('Expenditure Registry'!$F$4:$F$43,'Expenditure Registry'!$C$4:$C$43,A4) -> 19.9 | D4: =B4-C4 -> -19.9 | E4: =IF(B4=0,"",C4/B4) | F4: =IF(B4=0,"No Budget Set",IF(C4/B4>1,"Over Budget",IF(C4/B4>0.85,"Near Limit","On Track"))) -> No Budget Set
A5: Prototyping & 3D Printing | B5: 0 | C5: =SUMIFS('Expenditure Registry'!$F$4:$F$43,'Expenditure Registry'!$C$4:$C$43,A5) -> 0 | D5: =B5-C5 -> 0 | E5: =IF(B5=0,"",C5/B5) | F5: =IF(B5=0,"No Budget Set",IF(C5/B5>1,"Over Budget",IF(C5/B5>0.85,"Near Limit","On Track"))) -> No Budget Set
A6: AI/Compute & Cloud | B6: 0 | C6: =SUMIFS('Expenditure Registry'!$F$4:$F$43,'Expenditure Registry'!$C$4:$C$43,A6) -> 21.78 | D6: =B6-C6 -> -21.78 | E6: =IF(B6=0,"",C6/B6) | F6: =IF(B6=0,"No Budget Set",IF(C6/B6>1,"Over Budget",IF(C6/B6>0.85,"Near Limit","On Track"))) -> No Budget Set
A7: Software & Tools | B7: 0 | C7: =SUMIFS('Expenditure Registry'!$F$4:$F$43,'Expenditure Registry'!$C$4:$C$43,A7) -> 0 | D7: =B7-C7 -> 0 | E7: =IF(B7=0,"",C7/B7) | F7: =IF(B7=0,"No Budget Set",IF(C7/B7>1,"Over Budget",IF(C7/B7>0.85,"Near Limit","On Track"))) -> No Budget Set
A8: Datasets & Labeling | B8: 0 | C8: =SUMIFS('Expenditure Registry'!$F$4:$F$43,'Expenditure Registry'!$C$4:$C$43,A8) -> 0 | D8: =B8-C8 -> 0 | E8: =IF(B8=0,"",C8/B8) | F8: =IF(B8=0,"No Budget Set",IF(C8/B8>1,"Over Budget",IF(C8/B8>0.85,"Near Limit","On Track"))) -> No Budget Set
A9: Legal & Admin | B9: 0 | C9: =SUMIFS('Expenditure Registry'!$F$4:$F$43,'Expenditure Registry'!$C$4:$C$43,A9) -> 0 | D9: =B9-C9 -> 0 | E9: =IF(B9=0,"",C9/B9) | F9: =IF(B9=0,"No Budget Set",IF(C9/B9>1,"Over Budget",IF(C9/B9>0.85,"Near Limit","On Track"))) -> No Budget Set
A10: Marketing & Outreach | B10: 0 | C10: =SUMIFS('Expenditure Registry'!$F$4:$F$43,'Expenditure Registry'!$C$4:$C$43,A10) -> 0 | D10: =B10-C10 -> 0 | E10: =IF(B10=0,"",C10/B10) | F10: =IF(B10=0,"No Budget Set",IF(C10/B10>1,"Over Budget",IF(C10/B10>0.85,"Near Limit","On Track"))) -> No Budget Set
A11: Travel | B11: 0 | C11: =SUMIFS('Expenditure Registry'!$F$4:$F$43,'Expenditure Registry'!$C$4:$C$43,A11) -> 0 | D11: =B11-C11 -> 0 | E11: =IF(B11=0,"",C11/B11) | F11: =IF(B11=0,"No Budget Set",IF(C11/B11>1,"Over Budget",IF(C11/B11>0.85,"Near Limit","On Track"))) -> No Budget Set
A12: Office & Misc | B12: 0 | C12: =SUMIFS('Expenditure Registry'!$F$4:$F$43,'Expenditure Registry'!$C$4:$C$43,A12) -> 0 | D12: =B12-C12 -> 0 | E12: =IF(B12=0,"",C12/B12) | F12: =IF(B12=0,"No Budget Set",IF(C12/B12>1,"Over Budget",IF(C12/B12>0.85,"Near Limit","On Track"))) -> No Budget Set
A13: Other | B13: 0 | C13: =SUMIFS('Expenditure Registry'!$F$4:$F$43,'Expenditure Registry'!$C$4:$C$43,A13) -> 0 | D13: =B13-C13 -> 0 | E13: =IF(B13=0,"",C13/B13) | F13: =IF(B13=0,"No Budget Set",IF(C13/B13>1,"Over Budget",IF(C13/B13>0.85,"Near Limit","On Track"))) -> No Budget Set
A14: TOTAL | B14: =SUM(B4:B13) -> 0 | C14: =SUM(C4:C13) -> 41.68 | D14: =B14-C14 -> -41.68 | E14: =IF(B14=0,"",C14/B14)
A16: Type your budgeted amount (EUR) into the yellow cells. Actual Spent, Variance, % Used, and Status are all calculated from the Expenditure Registry — do not edit them.

Sheet Meeting Log
A1: Meeting Log
A2: Founders' meetings — agenda, decisions, and links to action items
A3: ID | B3: Date | C3: Time | D3: Type | E3: Attendees | F3: Agenda / Topic | G3: Key Decisions | H3: Linked Action Items | I3: Status | J3: Notes
A4: M001 | B4: 2026-01-10 | C4: 10:00 | D4: Weekly Sync | E4: Founder A, Founder B | F4: Kickoff — align on Q1 milestones (perception model MVP) — EXAMPLE, replace or delete | G4: Prioritize dataset collection before model training; target 500 labeled images by Feb | H4: A001, A002 | I4: Completed | J4: Reviewed docs/02_Roadmap.md milestones

Sheet Action Items
A1: Action Items
A2: Tasks raised in meetings — owners, due dates, status
A3: ID | B3: Source Meeting ID | C3: Date Raised | D3: Description | E3: Owner | F3: Priority | G3: Due Date | H3: Status | I3: Notes
A4: A001 | B4: M001 | C4: 2026-01-10 | D4: Set up datasets/ folder structure and labeling schema — EXAMPLE, replace or delete | E4: Founder B | F4: High | G4: 2026-01-20 | H4: In Progress | I4: See datasets/CLAUDE.md for ontology
